LICENSE
MANIFEST.in
README.md
requirements.txt
setup.cfg
setup.py
django_mp_poll.egg-info/PKG-INFO
django_mp_poll.egg-info/SOURCES.txt
django_mp_poll.egg-info/dependency_links.txt
django_mp_poll.egg-info/requires.txt
django_mp_poll.egg-info/top_level.txt
poll/__init__.py
poll/admin.py
poll/forms.py
poll/models.py
poll/translation.py
poll/urls.py
poll/utils.py
poll/views.py
poll/locale/en/LC_MESSAGES/django.mo
poll/locale/en/LC_MESSAGES/django.po
poll/locale/ru/LC_MESSAGES/django.mo
poll/locale/ru/LC_MESSAGES/django.po
poll/locale/uk/LC_MESSAGES/django.mo
poll/locale/uk/LC_MESSAGES/django.po
poll/migrations/0001_initial.py
poll/migrations/0002_poll_choice_order.py
poll/migrations/__init__.py
poll/static/poll/poll.css
poll/static/poll/poll.js
poll/templates/poll/form.html
poll/templates/poll/index.html
poll/templates/poll/result.html
poll/templatetags/__init__.py
poll/templatetags/poll.py