Metadata-Version: 1.1
Name: django-mp-poll
Version: 2.8
Summary: Django poll app
Home-page: https://github.com/pmaigutyak/mp-poll
Author: Paul Maigutyak
Author-email: pmaigutyak@gmail.com
License: MIT
Download-URL: https://github.com/pmaigutyak/mp-poll/archive/2.8.tar.gz
Platform: UNKNOWN
